CogniSolve/__init__.py
CogniSolve/pyalgorithms.py
CogniSolve-9.dist-info/METADATA
CogniSolve-9.dist-info/WHEEL
CogniSolve-9.dist-info/top_level.txt
CogniSolve-9.dist-info/RECORD
