Metadata-Version: 2.1
Name: CogniSolve
Version: 9
Summary: Algorithms in one python library.
Author: Andrei Sergeev
Author-email: andreiefremov135@gmail.com
Requires-Python: >=3.0
